Workbook

Sheet Read Me
A1: SALES PERFORMANCE ANALYSIS
A2: Objective | B2: Analyze sales, profit, product/category, regional and monthly trends using Excel.
A3: Dataset | B3: 600 rows of synthetic practice data; not real company data.
A4: Business questions | B4: What are sales and profit? Which category/region performs best? Which products drive sales? How do monthly sales change?
A5: Workflow | B5: Review Data; validate data; review Summary formulas/charts; build PivotTables; write verified insights.
A6: Excel skills | B6: SUM, SUMIF, COUNTIF, COUNTA, IFERROR, tables, filtering, PivotTables and charts.

Sheet Data
A1: Order_ID | B1: Order_Date | C1: Region | D1: Category | E1: Product | F1: Quantity | G1: Unit_Price | H1: Discount | I1: Sales | J1: Cost | K1: Profit | L1: Customer_Segment | M1: Month
A2: ORD-1381 | B2: 45659 | C2: East | D2: Office Supplies | E2: Stapler | F2: 6 | G2: 8.73 | H2: 0.05 | I2: 49.76 | J2: 37.82 | K2: 11.94 | L2: Consumer | M2: Jan
A3: ORD-1104 | B3: 45660 | C3: North | D3: Office Supplies | E3: Pen Pack | F3: 4 | G3: 15.76 | H3: 0.15 | I3: 53.58 | J3: 37.09 | K3: 16.49 | L3: Small Business | M3: Jan
A4: ORD-1575 | B4: 45660 | C4: North | D4: Furniture | E4: Bookshelf | F4: 2 | G4: 159.71 | H4: 0.15 | I4: 271.51 | J4: 258.11 | K4: 13.4 | L4: Corporate | M4: Jan
A5: ORD-1465 | B5: 45660 | C5: West | D5: Furniture | E5: Office Chair | F5: 1 | G5: 202.68 | H5: 0.05 | I5: 192.55 | J5: 149.2 | K5: 43.35 | L5: Small Business | M5: Jan
A6: ORD-1303 | B6: 45661 | C6: North | D6: Technology | E6: Headphones | F6: 1 | G6: 120.74 | H6: 0.1 | I6: 108.67 | J6: 89.83 | K6: 18.84 | L6: Consumer | M6: Jan
A7: ORD-1410 | B7: 45663 | C7: East | D7: Furniture | E7: Desk | F7: 2 | G7: 487.07 | H7: 0.05 | I7: 925.43 | J7: 725.59 | K7: 199.84 | L7: Small Business | M7: Jan
A8: ORD-1478 | B8: 45664 | C8: North | D8: Furniture | E8: Table | F8: 2 | G8: 327.63 | H8: 0.05 | I8: 622.5 | J8: 347.2 | K8: 275.3 | L8: Corporate | M8: Jan
A9: ORD-1415 | B9: 45664 | C9: East | D9: Furniture | E9: Office Chair | F9: 8 | G9: 187.22 | H9: 0.05 | I9: 1422.87 | J9: 962.93 | K9: 459.94 | L9: Corporate | M9: Jan
A10: ORD-1300 | B10: 45665 | C10: East | D10: Furniture | E10: Desk | F10: 1 | G10: 203.01 | H10: 0 | I10: 203.01 | J10: 123.47 | K10: 79.54 | L10: Small Business | M10: Jan
A11: ORD-1233 | B11: 45665 | C11: South | D11: Furniture | E11: Table | F11: 4 | G11: 143.03 | H11: 0 | I11: 572.12 | J11: 405.11 | K11: 167.01 | L11: Consumer | M11: Jan
A12: ORD-1540 | B12: 45665 | C12: East | D12: Office Supplies | E12: Printer Paper | F12: 7 | G12: 18.12 | H12: 0.1 | I12: 114.16 | J12: 73.18 | K12: 40.98 | L12: Small Business | M12: Jan
A13: ORD-1170 | B13: 45666 | C13: South | D13: Office Supplies | E13: Stapler | F13: 4 | G13: 19.3 | H13: 0 | I13: 77.2 | J13: 57.28 | K13: 19.92 | L13: Corporate | M13: Jan
... A601: ORD-1401 | B601: 46022 | C601: West | D601: Technology | E601: Mouse | F601: 7 | G601: 45.65 | H601: 0 | I601: 319.55 | J601: 237.65 | K601: 81.9 | L601: Consumer | M601: Dec

Sheet Summary
A1: SALES PERFORMANCE SUMMARY
A2: Metric | B2: Value | C2: Interpretation
A3: Total Sales | B3: =SUM(Data!I:I) -> 306604.7 | C3: Revenue after discount
A4: Total Profit | B4: =SUM(Data!K:K) -> 85193.96 | C4: Sales minus estimated cost
A5: Order Records | B5: =COUNTA(Data!A:A)-1 -> 600 | C5: Number of records
A6: Units Sold | B6: =SUM(Data!F:F) -> 2616 | C6: Total quantity
A7: Profit Margin | B7: =IFERROR(B3/B2,0) -> 0 | C7: Profit divided by sales
A8: Average Sales per Order | B8: =IFERROR(B2/B4,0) -> 0 | C8: Average per record
A10: Category | B10: Sales | C10: Profit | D10: Orders
A11: Technology | B11: =SUMIF(Data!D:D,A11,Data!I:I) -> 163270.82 | C11: =SUMIF(Data!D:D,A11,Data!K:K) -> 46346.41 | D11: =COUNTIF(Data!D:D,A11) -> 183
A12: Furniture | B12: =SUMIF(Data!D:D,A12,Data!I:I) -> 129150.14 | C12: =SUMIF(Data!D:D,A12,Data!K:K) -> 34921.76 | D12: =COUNTIF(Data!D:D,A12) -> 146
A13: Office Supplies | B13: =SUMIF(Data!D:D,A13,Data!I:I) -> 14183.74 | C13: =SUMIF(Data!D:D,A13,Data!K:K) -> 3925.79 | D13: =COUNTIF(Data!D:D,A13) -> 271
A16: Region | B16: Sales | C16: Profit | D16: Orders
A17: North | B17: =SUMIF(Data!C:C,A17,Data!I:I) -> 71424.03 | C17: =SUMIF(Data!C:C,A17,Data!K:K) -> 18923.67 | D17: =COUNTIF(Data!C:C,A17) -> 146
A18: South | B18: =SUMIF(Data!C:C,A18,Data!I:I) -> 90898.01 | C18: =SUMIF(Data!C:C,A18,Data!K:K) -> 25329.84 | D18: =COUNTIF(Data!C:C,A18) -> 137
A19: East | B19: =SUMIF(Data!C:C,A19,Data!I:I) -> 61232.59 | C19: =SUMIF(Data!C:C,A19,Data!K:K) -> 16160.79 | D19: =COUNTIF(Data!C:C,A19) -> 169
A20: West | B20: =SUMIF(Data!C:C,A20,Data!I:I) -> 83050.07 | C20: =SUMIF(Data!C:C,A20,Data!K:K) -> 24779.66 | D20: =COUNTIF(Data!C:C,A20) -> 148
A23: Month | B23: Sales | C23: Profit
A24: Jan | B24: =SUMIF(Data!M:M,A24,Data!I:I) -> 25464.58 | C24: =SUMIF(Data!M:M,A24,Data!K:K) -> 6812.69
A25: Feb | B25: =SUMIF(Data!M:M,A25,Data!I:I) -> 35226.06 | C25: =SUMIF(Data!M:M,A25,Data!K:K) -> 10040.1
A26: Mar | B26: =SUMIF(Data!M:M,A26,Data!I:I) -> 25106.02 | C26: =SUMIF(Data!M:M,A26,Data!K:K) -> 4946.38
A27: Apr | B27: =SUMIF(Data!M:M,A27,Data!I:I) -> 22486.24 | C27: =SUMIF(Data!M:M,A27,Data!K:K) -> 5724.03
A28: May | B28: =SUMIF(Data!M:M,A28,Data!I:I) -> 18704.6 | C28: =SUMIF(Data!M:M,A28,Data!K:K) -> 4719.56
A29: Jun | B29: =SUMIF(Data!M:M,A29,Data!I:I) -> 16812.96 | C29: =SUMIF(Data!M:M,A29,Data!K:K) -> 4457.91
A30: Jul | B30: =SUMIF(Data!M:M,A30,Data!I:I) -> 32092.44 | C30: =SUMIF(Data!M:M,A30,Data!K:K) -> 9542.69
A31: Aug | B31: =SUMIF(Data!M:M,A31,Data!I:I) -> 34109.6 | C31: =SUMIF(Data!M:M,A31,Data!K:K) -> 11726.03
A32: Sep | B32: =SUMIF(Data!M:M,A32,Data!I:I) -> 20780.26 | C32: =SUMIF(Data!M:M,A32,Data!K:K) -> 5595.59
A33: Oct | B33: =SUMIF(Data!M:M,A33,Data!I:I) -> 28555.53 | C33: =SUMIF(Data!M:M,A33,Data!K:K) -> 7055.93
A34: Nov | B34: =SUMIF(Data!M:M,A34,Data!I:I) -> 27132.58 | C34: =SUMIF(Data!M:M,A34,Data!K:K) -> 9380.82
A35: Dec | B35: =SUMIF(Data!M:M,A35,Data!I:I) -> 20133.83 | C35: =SUMIF(Data!M:M,A35,Data!K:K) -> 5192.23

Sheet Analysis Tasks
A1: TASK | B1: WHAT TO DO | C1: OUTPUT
A2: Data quality | B2: Check blanks, duplicate Order_IDs, date range and numeric columns. | C2: Document issues.
A3: KPI review | B3: Review sales, profit, units, order count and margin. | C3: Explain each KPI.
A4: Category | B4: Compare sales and profit by category. | C4: Find category leaders.
A5: Region | B5: Compare sales and profit across regions. | C5: Explain differences.
A6: Monthly trend | B6: Explain monthly peaks and dips. | C6: Use line chart; mention synthetic data.
A7: Product analysis | B7: Create PivotTable: Product in Rows; Sales and Profit in Values. | C7: Identify top five products.
A8: Recommendations | B8: Write three recommendations supported by verified numbers. | C8: Business communication.
A9: Portfolio | B9: Add workbook screenshots and verified findings to README. | C9: GitHub polish.
